litime_ble/__init__.py
litime_ble/__main__.py
litime_ble/cli.py
litime_ble/client.py
litime_ble/discovery.py
litime_ble/errors.py
litime_ble/logging.py
litime_ble/models.py
litime_ble-0.2.2.dist-info/licenses/LICENSE
litime_ble-0.2.2.dist-info/METADATA
litime_ble-0.2.2.dist-info/WHEEL
litime_ble-0.2.2.dist-info/entry_points.txt
litime_ble-0.2.2.dist-info/top_level.txt
litime_ble-0.2.2.dist-info/RECORD
