Metadata-Version: 2.4
Name: litime-ble
Version: 0.2.2
Summary: Li Time Bluetooth battery reader via BLE (Python, Bleak)
Author: Cameron K. Brooks
License-Expression: MIT
Keywords: bluetooth,ble,battery,litime,solar,power
Classifier: Development Status :: 4 - Beta
Classifier: Intended Audience :: Developers
Classifier: Intended Audience :: End Users/Desktop
Classifier: Operating System :: OS Independent
Classifier: Programming Language :: Python :: 3
Classifier: Programming Language :: Python :: 3.9
Classifier: Programming Language :: Python :: 3.10
Classifier: Programming Language :: Python :: 3.11
Classifier: Programming Language :: Python :: 3.12
Classifier: Topic :: Home Automation
Classifier: Topic :: Scientific/Engineering
Classifier: Topic :: System :: Hardware
Classifier: Topic :: System :: Monitoring
Classifier: Topic :: Utilities
Requires-Python: >=3.9
License-File: LICENSE
Requires-Dist: bleak>=0.22
Provides-Extra: test
Requires-Dist: pytest>=8.2; extra == "test"
Requires-Dist: pytest-asyncio>=1.2; extra == "test"
Dynamic: license-file
